django_assets/__init__.py
django_assets/env.py
django_assets/filter.py
django_assets/finders.py
django_assets/glob.py
django_assets/loaders.py
django_assets/manifest.py
django_assets/models.py
django_assets/pytest_plugin.py
django_assets/settings.py
django_assets/management/__init__.py
django_assets/management/commands/__init__.py
django_assets/management/commands/assets.py
django_assets/templatetags/__init__.py
django_assets/templatetags/assets.py
django_assets-2.0.dist-info/LICENSE
django_assets-2.0.dist-info/METADATA
django_assets-2.0.dist-info/WHEEL
django_assets-2.0.dist-info/entry_points.txt
django_assets-2.0.dist-info/top_level.txt
django_assets-2.0.dist-info/RECORD
